art_deco/__init__.py
art_deco/core/__init__.py
art_deco/core/arg_processors/__init__.py
art_deco/core/arg_processors/api.py
art_deco/core/arg_processors/dynamic_decorator.py
art_deco/core/arg_processors/processing.py
art_deco/core/arg_processors/static_decorator.py
art_deco/core/specs/__init__.py
art_deco/core/specs/dynamic_arg_specs.py
art_deco/core/specs/dynamic_inspector.py
art_deco/core/specs/static_arg_specs.py
art_deco/core/specs/static_inspector.py
art_deco/core/specs/type_hints_parsers.py
art_deco/hack_args/__init__.py
art_deco/hack_args/marks.py
art_deco/hack_args/processor.py
art_deco/utils/__init__.py
art_deco/utils/dictionary.py
art_deco/utils/dynamic_args.py
art_deco/utils/inspection_utils.py
art_deco/utils/typing_utils.py
art_deco-0.0.1.dist-info/LICENSE
art_deco-0.0.1.dist-info/METADATA
art_deco-0.0.1.dist-info/WHEEL
art_deco-0.0.1.dist-info/top_level.txt
art_deco-0.0.1.dist-info/RECORD
