Metadata-Version: 2.1
Name: art-deco
Version: 0.0.1
Summary: Via decorators, make complex processing of function or method arguments effortless.
Author: Cristian Matache
Requires-Python: >=3.7
License-File: LICENSE
Requires-Dist: wrapt
Requires-Dist: typing-extensions
